winzy_text_on_image/__init__.py
winzy_text_on_image-0.1.dist-info/LICENSE
winzy_text_on_image-0.1.dist-info/METADATA
winzy_text_on_image-0.1.dist-info/WHEEL
winzy_text_on_image-0.1.dist-info/entry_points.txt
winzy_text_on_image-0.1.dist-info/top_level.txt
winzy_text_on_image-0.1.dist-info/RECORD
