Metadata-Version: 2.1
Name: winzy-text-on-image
Version: 0.1
Summary: Add text to an image.
Author: Sukhbinder Singh
License: Apache-2.0
Project-URL: Homepage, https://github.com/sukhbinder/winzy-text-on-image
Project-URL: Changelog, https://github.com/sukhbinder/winzy-text-on-image/releases
Project-URL: Issues, https://github.com/sukhbinder/winzy-text-on-image/issues
Project-URL: CI, https://github.com/sukhbinder/winzy-text-on-image/actions
Classifier: License :: OSI Approved :: Apache Software License
License-File: LICENSE
Requires-Dist: winzy
Requires-Dist: pillow
Provides-Extra: test
Requires-Dist: pytest ; extra == 'test'
